{
  "stop_state": "835962f5448b20d66a7e03b6e7514802", 
  "event_str": "TouchEvent", 
  "tag": "2021-08-14_190824", 
  "event": {
    "y": null, 
    "x": null, 
    "view": {
      "content_description": "Navigate up", 
      "resource_id": null, 
      "text": null, 
      "editable": false, 
      "visible": true, 
      "is_password": false, 
      "focused": false, 
      "clickable": true, 
      "checkable": false, 
      "size": "137*147", 
      "scrollable": false, 
      "checked": false, 
      "package": "com.twitter.android", 
      "long_clickable": false, 
      "selected": false, 
      "enabled": true, 
      "bounds": [
        [
          0, 
          63
        ], 
        [
          137, 
          210
        ]
      ], 
      "class": "android.widget.ImageButton", 
      "focusable": true
    }, 
    "id": 0, 
    "event_type": "touch"
  }, 
  "start_state": "b6bd60a519abcc77f7da0fc05e0b7133"
}