{
  "stop_state": "bc50baefaaaaa74c6f9f749c18738b92", 
  "event_str": "TouchEvent", 
  "tag": "2021-08-13_214257", 
  "event": {
    "y": null, 
    "x": null, 
    "view": {
      "content_description": null, 
      "resource_id": null, 
      "text": "by www.intuix.com.br", 
      "editable": false, 
      "visible": true, 
      "is_password": false, 
      "focused": false, 
      "clickable": true, 
      "checkable": false, 
      "size": "404*52", 
      "scrollable": false, 
      "checked": false, 
      "package": "com.cpuid.cpu_z", 
      "long_clickable": false, 
      "selected": false, 
      "enabled": true, 
      "bounds": [
        [
          338, 
          378
        ], 
        [
          742, 
          430
        ]
      ], 
      "class": "android.view.View", 
      "focusable": false
    }, 
    "id": 4, 
    "event_type": "touch"
  }, 
  "start_state": "fbb5f5d8f7719f0cd6157192f19b83b8"
}