{
  "stop_state": "31939686235b22b87dab9fe72b929184", 
  "event_str": "TouchEvent", 
  "tag": "2021-08-13_202107", 
  "event": {
    "y": null, 
    "x": null, 
    "view": {
      "content_description": null, 
      "resource_id": null, 
      "text": null, 
      "editable": false, 
      "visible": true, 
      "is_password": false, 
      "focused": false, 
      "clickable": true, 
      "checkable": false, 
      "size": "233*126", 
      "scrollable": false, 
      "checked": false, 
      "package": "com.cpuid.cpu_z", 
      "long_clickable": false, 
      "selected": false, 
      "enabled": true, 
      "bounds": [
        [
          188, 
          189
        ], 
        [
          421, 
          315
        ]
      ], 
      "class": "android.app.ActionBar$Tab", 
      "focusable": true
    }, 
    "id": 3, 
    "event_type": "touch"
  }, 
  "start_state": "3c473656c8d971ff561f6f5756ea0990"
}