{
  "stop_state": "e97aae32acefe51ceaf6cec3e7c41a1e", 
  "event_str": "TouchEvent", 
  "tag": "2021-08-13_210902", 
  "event": {
    "y": null, 
    "x": null, 
    "view": {
      "content_description": null, 
      "resource_id": null, 
      "text": "AKedOLRjw8XiolvtC8EH_miot12LBnBw24z4dQlXEygk=s48-c-k-c0x00ffffff-no-rj", 
      "editable": false, 
      "visible": true, 
      "is_password": false, 
      "focused": false, 
      "clickable": true, 
      "checkable": false, 
      "size": "152*150", 
      "scrollable": false, 
      "checked": false, 
      "package": "com.cpuid.cpu_z", 
      "long_clickable": false, 
      "selected": false, 
      "enabled": true, 
      "bounds": [
        [
          464, 
          178
        ], 
        [
          616, 
          328
        ]
      ], 
      "class": "android.widget.Button", 
      "focusable": true
    }, 
    "id": 2, 
    "event_type": "touch"
  }, 
  "start_state": "4fbd896158416dbce5af7f6c8b5cfa42"
}