{
  "stop_state": "b200087599a8f380118f16d515d85c71", 
  "event_str": "FillUIEvent", 
  "tag": "2021-08-22_165959", 
  "event": {
    "views_str": [
      "de66675516f8a67f71e60835fbe01eae", 
      "30a379e52f8b10288d40e121172cf505"
    ], 
    "event_type": "fill_UI", 
    "views": [
      {
        "content_description": null, 
        "resource_id": "com.eleybourn.bookcatalogue:id/author", 
        "text": "Auteur", 
        "visible": true, 
        "checkable": false, 
        "children": [], 
        "size": "1050*148", 
        "checked": false, 
        "temp_id": 14, 
        "selected": false, 
        "child_count": 0, 
        "content_free_signature": "[class]android.widget.EditText[resource_id]com.eleybourn.bookcatalogue:id/author", 
        "is_password": false, 
        "parent": 13, 
        "focusable": true, 
        "editable": true, 
        "focused": true, 
        "clickable": true, 
        "class": "android.widget.EditText", 
        "scrollable": false, 
        "package": "com.eleybourn.bookcatalogue", 
        "long_clickable": true, 
        "view_str": "de66675516f8a67f71e60835fbe01eae", 
        "enabled": true, 
        "bounds": [
          [
            15, 
            219
          ], 
          [
            1065, 
            367
          ]
        ], 
        "signature": "[class]android.widget.EditText[resource_id]com.eleybourn.bookcatalogue:id/author[text]Auteur[enabled,,]"
      }, 
      {
        "content_description": null, 
        "resource_id": "com.eleybourn.bookcatalogue:id/title", 
        "text": "Titel", 
        "visible": true, 
        "checkable": false, 
        "children": [], 
        "size": "1050*148", 
        "checked": false, 
        "temp_id": 15, 
        "selected": false, 
        "child_count": 0, 
        "content_free_signature": "[class]android.widget.EditText[resource_id]com.eleybourn.bookcatalogue:id/title", 
        "is_password": false, 
        "parent": 13, 
        "focusable": true, 
        "editable": true, 
        "focused": false, 
        "clickable": true, 
        "class": "android.widget.EditText", 
        "scrollable": false, 
        "package": "com.eleybourn.bookcatalogue", 
        "long_clickable": true, 
        "view_str": "30a379e52f8b10288d40e121172cf505", 
        "enabled": true, 
        "bounds": [
          [
            15, 
            367
          ], 
          [
            1065, 
            515
          ]
        ], 
        "signature": "[class]android.widget.EditText[resource_id]com.eleybourn.bookcatalogue:id/title[text]Titel[enabled,,]"
      }
    ]
  }, 
  "start_state": "ca97218bb912d562bf37eee8ef1e557a"
}