{
  "stop_state": "41dd468a55d265497583ae7c76802c8d", 
  "event_str": "TouchEvent", 
  "tag": "2021-08-22_191806", 
  "event": {
    "y": null, 
    "x": null, 
    "view": {
      "content_description": null, 
      "resource_id": null, 
      "text": null, 
      "editable": false, 
      "visible": true, 
      "is_password": false, 
      "focused": false, 
      "clickable": true, 
      "checkable": false, 
      "size": "784*144", 
      "scrollable": false, 
      "checked": false, 
      "package": "com.eleybourn.bookcatalogue", 
      "long_clickable": false, 
      "selected": false, 
      "enabled": true, 
      "bounds": [
        [
          272, 
          204
        ], 
        [
          1056, 
          348
        ]
      ], 
      "class": "android.widget.LinearLayout", 
      "focusable": false
    }, 
    "id": 0, 
    "event_type": "touch"
  }, 
  "start_state": "e48987914827b0e91ff697d569197bbd"
}